mailchimp/config.py
mailchimp/request.py
mailchimp/exceptions.py
mailchimp/__init__.py
mailchimp/objects/mc_list.py
mailchimp/objects/mc_list_stats.py
mailchimp/objects/mc_location.py
mailchimp/objects/mc_link.py
mailchimp/objects/mc_contact.py
mailchimp/objects/mc_campaign_defaults.py
mailchimp/objects/mc_member.py
mailchimp/objects/__init__.py
mailchimp/objects/base_object.py
Mailchimp_Python-0.1.0.dist-info/metadata.json
Mailchimp_Python-0.1.0.dist-info/DESCRIPTION.rst
Mailchimp_Python-0.1.0.dist-info/RECORD
Mailchimp_Python-0.1.0.dist-info/WHEEL
Mailchimp_Python-0.1.0.dist-info/METADATA
Mailchimp_Python-0.1.0.dist-info/top_level.txt
tests/objects/test_mc_link.py
tests/objects/test_mc_campaign_defaults.py
tests/objects/test_mc_list.py
tests/objects/test_mc_location.py
tests/objects/test_mc_contact.py
tests/objects/test_mc_list_stats.py
tests/objects/test_mc_member.py
tests/objects/__init__.py
